vidyut-0.4.0.dist-info/METADATA
vidyut-0.4.0.dist-info/WHEEL
vidyut-0.4.0.dist-info/licenses/LICENSE.md
vidyut.libs/libgcc_s-5b5488a6.so.1
vidyut/docs/requirements.txt
vidyut/docs/.gitignore
vidyut/docs/Makefile
vidyut/docs/source/chandas.rst
vidyut/docs/source/tutorial.rst
vidyut/docs/source/changes.rst
vidyut/docs/source/index.rst
vidyut/docs/source/kosha.rst
vidyut/docs/source/sandhi.rst
vidyut/docs/source/prakriya.rst
vidyut/docs/source/introduction.rst
vidyut/docs/source/api.rst
vidyut/docs/source/conf.py
vidyut/docs/source/lipi.rst
vidyut/docs/source/cheda.rst
vidyut/docs/make.bat
vidyut/cheda.py
vidyut/kosha.pyi
vidyut/cheda.pyi
vidyut/prakriya.pyi
vidyut/sandhi.py
vidyut/lipi.py
vidyut/prakriya.py
vidyut/chandas.py
vidyut/__init__.py
vidyut/sandhi.pyi
vidyut/kosha.py
vidyut/py.typed
CHANGES.rst
LICENSE.md
README.md
vidyut/vidyut.abi3.so
vidyut-0.4.0.dist-info/RECORD
