Metadata-Version: 2.4
Name: vidyut
Version: 0.4.0
Classifier: Programming Language :: Rust
Classifier: Programming Language :: Python :: Implementation :: CPython
Classifier: Programming Language :: Python :: Implementation :: PyPy
License-File: LICENSE.md
Summary: A high-performance Sanskrit toolkit
Requires-Python: >=3.7
